api/__init__.py
api/grpc.py
api/upload.py
gateway/__init__.py
gateway/polling.py
gateway/websocket.py
models/__init__.py
models/channel.py
models/community.py
models/message.py
parsers/__init__.py
parsers/channel.py
parsers/community.py
parsers/message.py
parsers/user.py
proto/__init__.py
proto/reader.py
rootpy_self-0.1.0.dist-info/licenses/LICENSE
rootpy_self-0.1.0.dist-info/METADATA
rootpy_self-0.1.0.dist-info/WHEEL
rootpy_self-0.1.0.dist-info/top_level.txt
rootpy_self-0.1.0.dist-info/RECORD
