Metadata-Version: 2.4
Name: rootpy-self
Version: 0.1.0
Summary: Root App self wrapper in python
Home-page: https://github.com/luvelge/rootpy-self
Author: luvelge
Author-email: luvelge <gala-shiny-reverse@duck.com>
License: MIT
Project-URL: Homepage, https://github.com/luvelge/rootpy-self
Project-URL: Repository, https://github.com/luvelge/rootpy-self
Project-URL: Issues, https://github.com/luvelge/rootpy-self/issues
Keywords: root,api,bot,client,self
Classifier: Development Status :: 3 - Alpha
Classifier: Intended Audience :: Developers
Classifier: License :: OSI Approved :: MIT License
Classifier: Operating System :: OS Independent
Classifier: Programming Language :: Python :: 3
Classifier: Programming Language :: Python :: 3.8
Classifier: Programming Language :: Python :: 3.9
Classifier: Programming Language :: Python :: 3.10
Classifier: Programming Language :: Python :: 3.11
Classifier: Programming Language :: Python :: 3.12
Requires-Python: >=3.8
License-File: LICENSE
Requires-Dist: requests>=2.28.0
Requires-Dist: websocket-client>=1.4.0
Dynamic: author
Dynamic: home-page
Dynamic: license-file
Dynamic: requires-python
